{
  "animations": [
    {
      "id": "animationDragon",
      "title": "",
      "fullscreen": false,
      "loop": true,
      "loopSection": [82, 287]
    },
    {
      "id": "animationAccommodationVergence",
      "title": "Accommodation & Vergence",
      "fullscreen": false,
      "loop": true,
      "loopSection": null
    },
    {
      "id": "animationImpairedVision",
      "title": "Impaired vision",
      "fullscreen": true,
      "states": ["normal eye", "myopia", "hyperopia", "astigmatism"],
      "toggle": "corrected"
    },
    {
      "id": "animationZwei",
      "title": "Animation Zwei",
      "fullscreen": false
    },
    {
      "id": "animationDrei",
      "title": "Animation Drei",
      "fullscreen": false
    },
    {
      "id": "animationLateralOrganization",
      "title": " Lateral organization",
      "fullscreen": false,
      "scroll": true
    },
    {
      "id": "animationRetinalCellTypes",
      "title": "Retinal Cell Types",
      "fullscreen": false,
      "clickTriggered": true,
      "states": [
        "photoreceptors",
        "horizontal cells",
        "bipolar cells",
        "amacrine cells",
        "ganglion cells"
      ]
    },
    {
      "id": "animationEyeMovements",
      "title": "Eye Movements",
      "fullscreen": true,
      "multiple": true,
      "states": {
        "age": "Give the ages of the people",
        "free": "Just look at the picture"
      }
    }
  ]
}
