{"v":"5.10.0","fr":24,"ip":0,"op":228,"w":1920,"h":1920,"nm":"2-auge-animready-loop","ddd":0,"assets":[],"layers":[{"ddd":0,"ind":1,"ty":4,"nm":"Ebene 13 Konturen","sr":1,"ks":{"o":{"a":1,"k":[{"i":{"x":[0.667],"y":[1]},"o":{"x":[0.333],"y":[0]},"t":-80,"s":[0]},{"t":-72,"s":[100]}],"ix":11},"r":{"a":0,"k":0,"ix":10},"p":{"s":true,"x":{"a":1,"k":[{"i":{"x":[0.709],"y":[1]},"o":{"x":[0.476],"y":[0]},"t":-108,"s":[1088.398]},{"i":{"x":[0.709],"y":[1]},"o":{"x":[0.531],"y":[0]},"t":-48,"s":[1011.773]},{"i":{"x":[0.283],"y":[1]},"o":{"x":[0.531],"y":[0]},"t":-36,"s":[1011.773]},{"t":-12,"s":[416.273]}],"ix":3},"y":{"a":1,"k":[{"i":{"x":[0.709],"y":[1]},"o":{"x":[0.476],"y":[0]},"t":-108,"s":[485.282]},{"i":{"x":[0.709],"y":[1]},"o":{"x":[0.333],"y":[0]},"t":-48,"s":[984.032]},{"t":-36,"s":[984.032]}],"ix":4}},"a":{"a":0,"k":[82.199,82.198,0],"ix":1,"l":2},"s":{"a":1,"k":[{"i":{"x":[0.511,0.511,0.667],"y":[1,1,1]},"o":{"x":[0.512,0.512,0.333],"y":[0,0,0]},"t":-108,"s":[11,11,100]},{"t":-36,"s":[100,100,100]}],"ix":6,"l":2}},"ao":0,"shapes":[{"ty":"gr","it":[{"ind":0,"ty":"sh","ix":1,"ks":{"a":1,"k":[{"i":{"x":0.667,"y":1},"o":{"x":0.333,"y":0},"t":-36,"s":[{"i":[[0,-45.259],[45.259,0],[0,45.259],[-45.258,0]],"o":[[0,45.259],[-45.258,0],[0,-45.259],[45.259,0]],"v":[[81.949,0],[-0.001,81.948],[-81.949,0],[-0.001,-81.948]],"c":true}]},{"t":-12,"s":[{"i":[[0,-97.065],[26.895,0.926],[0,97.065],[-18.398,0.625]],"o":[[0,97.065],[-14.523,-0.5],[0,-97.065],[26.896,-0.914]],"v":[[48.727,5.218],[0,180.968],[-35.227,-7.23],[0,-170.532]],"c":true}]}],"ix":2},"nm":"Pfad 1","mn":"ADBE Vector Shape - Group","hd":false},{"ty":"fl","c":{"a":0,"k":[0,0,0,1],"ix":4},"o":{"a":0,"k":100,"ix":5},"r":1,"bm":0,"nm":"Fläche 1","mn":"ADBE Vector Graphic - Fill","hd":false},{"ty":"tr","p":{"a":0,"k":[82.198,82.198],"ix":2},"a":{"a":0,"k":[0,0],"ix":1},"s":{"a":0,"k":[100,100],"ix":3},"r":{"a":0,"k":0,"ix":6},"o":{"a":0,"k":100,"ix":7},"sk":{"a":0,"k":0,"ix":4},"sa":{"a":0,"k":0,"ix":5},"nm":"Transformieren"}],"nm":"Gruppe 1","np":2,"cix":2,"bm":0,"ix":1,"mn":"ADBE Vector Group","hd":false}],"ip":-108,"op":228,"st":-36,"ct":1,"bm":0},{"ddd":0,"ind":3,"ty":4,"nm":"iris","sr":1,"ks":{"o":{"a":1,"k":[{"i":{"x":[0.667],"y":[1]},"o":{"x":[0.333],"y":[0]},"t":-84,"s":[0]},{"t":-72,"s":[100]}],"ix":11},"r":{"a":0,"k":0,"ix":10},"p":{"s":true,"x":{"a":1,"k":[{"i":{"x":[0.709],"y":[1]},"o":{"x":[0.476],"y":[0]},"t":-108,"s":[1088.398]},{"i":{"x":[0.709],"y":[1]},"o":{"x":[0.531],"y":[0]},"t":-48,"s":[1011.773]},{"i":{"x":[0.283],"y":[1]},"o":{"x":[0.531],"y":[0]},"t":-36,"s":[1011.773]},{"t":-12,"s":[406.773]}],"ix":3},"y":{"a":1,"k":[{"i":{"x":[0.709],"y":[1]},"o":{"x":[0.476],"y":[0]},"t":-108,"s":[485.282]},{"i":{"x":[0.709],"y":[1]},"o":{"x":[0.333],"y":[0]},"t":-48,"s":[984.032]},{"t":-36,"s":[984.032]}],"ix":4}},"a":{"a":0,"k":[168.897,168.897,0],"ix":1,"l":2},"s":{"a":1,"k":[{"i":{"x":[0.511,0.511,0.667],"y":[1,1,1]},"o":{"x":[0.512,0.512,0.333],"y":[0,0,0]},"t":-108,"s":[11,11,100]},{"t":-36,"s":[100,100,100]}],"ix":6,"l":2}},"ao":0,"shapes":[{"ty":"gr","it":[{"ind":0,"ty":"sh","ix":1,"ks":{"a":1,"k":[{"i":{"x":0.833,"y":0.833},"o":{"x":0.333,"y":0},"t":-36,"s":[{"i":[[0,-90.518],[90.518,0],[0,90.518],[-90.518,0]],"o":[[0,90.518],[-90.518,0],[0,-90.518],[90.518,0]],"v":[[163.897,0],[0,163.897],[-163.897,0],[0,-163.897]],"c":true}]},{"i":{"x":0.667,"y":1},"o":{"x":0.167,"y":0.167},"t":-21,"s":[{"i":[[0.124,-109.043],[64.649,3.661],[3.761,162.977],[-64.29,-1.522]],"o":[[-0.115,101.098],[-58.353,-3.305],[-3.816,-165.366],[67.937,1.609]],"v":[[174.666,-3.989],[77.141,289.306],[-55.97,6.991],[70.08,-292.51]],"c":true}]},{"t":-12,"s":[{"i":[[3,-134.938],[-83,-137.564],[0,223.693],[-42.5,53.875]],"o":[[-3,83.562],[-37.5,-28.064],[0,-223.693],[-76,134]],"v":[[21.227,8.781],[124.727,411.407],[-24.773,0.875],[112.602,-397.157]],"c":true}]}],"ix":2},"nm":"Pfad 1","mn":"ADBE Vector Shape - Group","hd":false},{"ty":"st","c":{"a":0,"k":[0,0,0,1],"ix":3},"o":{"a":0,"k":100,"ix":4},"w":{"a":0,"k":2,"ix":5},"lc":2,"lj":1,"ml":10,"bm":0,"nm":"Kontur 1","mn":"ADBE Vector Graphic - Stroke","hd":false},{"ty":"fl","c":{"a":1,"k":[{"i":{"x":[0.667],"y":[1]},"o":{"x":[0.333],"y":[0]},"t":-36,"s":[0,1,1,1]},{"i":{"x":[0.667],"y":[1]},"o":{"x":[0.333],"y":[0]},"t":0,"s":[0.002599000232,0.662745118141,0.002599000232,1]},{"i":{"x":[0.667],"y":[1]},"o":{"x":[0.333],"y":[0]},"t":60,"s":[0.568627476692,0.501960813999,0.458823561668,1]},{"i":{"x":[0.667],"y":[1]},"o":{"x":[0.333],"y":[0]},"t":108,"s":[0.376470625401,0.21960785985,0.074509806931,1]},{"i":{"x":[0.667],"y":[1]},"o":{"x":[0.333],"y":[0]},"t":156,"s":[0,1,1,1]},{"t":228,"s":[0.003921568859,0.662745118141,0.003921568859,1]}],"ix":4},"o":{"a":0,"k":100,"ix":5},"r":1,"bm":0,"nm":"Fläche 1","mn":"ADBE Vector Graphic - Fill","hd":false},{"ty":"tr","p":{"a":0,"k":[168.897,168.897],"ix":2},"a":{"a":0,"k":[0,0],"ix":1},"s":{"a":0,"k":[100,100],"ix":3},"r":{"a":0,"k":0,"ix":6},"o":{"a":0,"k":100,"ix":7},"sk":{"a":0,"k":0,"ix":4},"sa":{"a":0,"k":0,"ix":5},"nm":"Transformieren"}],"nm":"Gruppe 1","np":3,"cix":2,"bm":0,"ix":1,"mn":"ADBE Vector Group","hd":false}],"ip":-108,"op":228,"st":-36,"ct":1,"bm":0},{"ddd":0,"ind":4,"ty":4,"nm":".lensHighlight.highlighterIlluFill","cl":"lensHighlight highlighterIlluFill","sr":1,"ks":{"o":{"a":0,"k":100,"ix":11},"r":{"a":0,"k":0,"ix":10},"p":{"s":true,"x":{"a":0,"k":554.773,"ix":3},"y":{"a":0,"k":984.032,"ix":4}},"a":{"a":0,"k":[332.794,332.794,0],"ix":1,"l":2},"s":{"a":0,"k":[100,100,100],"ix":6,"l":2}},"ao":0,"shapes":[{"ty":"gr","it":[{"ind":0,"ty":"sh","ix":1,"ks":{"a":0,"k":{"i":[[0,-150.498],[55.228,0],[0,150.498],[-55.229,0]],"o":[[0,150.498],[-55.228,0],[0,-150.498],[55.229,0]],"v":[[108.727,-4.532],[8.727,267.968],[-91.273,-4.532],[8.727,-277.032]],"c":true},"ix":2},"nm":"Pfad 1","mn":"ADBE Vector Shape - Group","hd":false},{"ty":"st","c":{"a":0,"k":[0,0,0,1],"ix":3},"o":{"a":0,"k":100,"ix":4},"w":{"a":0,"k":2,"ix":5},"lc":2,"lj":1,"ml":10,"bm":0,"nm":"Kontur 1","mn":"ADBE Vector Graphic - Stroke","hd":false},{"ty":"fl","c":{"a":0,"k":[1,1,1,1],"ix":4},"o":{"a":0,"k":100,"ix":5},"r":1,"bm":0,"nm":"Fläche 1","mn":"ADBE Vector Graphic - Fill","hd":false},{"ty":"tr","p":{"a":0,"k":[332.794,332.794],"ix":2},"a":{"a":0,"k":[0,0],"ix":1},"s":{"a":0,"k":[100,103.238],"ix":3},"r":{"a":0,"k":0,"ix":6},"o":{"a":0,"k":100,"ix":7},"sk":{"a":0,"k":0,"ix":4},"sa":{"a":0,"k":0,"ix":5},"nm":"Transformieren"}],"nm":"Gruppe 1","np":3,"cix":2,"bm":0,"ix":1,"mn":"ADBE Vector Group","hd":false},{"ty":"tm","s":{"a":0,"k":0,"ix":1},"e":{"a":0,"k":100,"ix":2},"o":{"a":0,"k":0,"ix":3},"m":1,"ix":2,"nm":"Pfade trimmen 1","mn":"ADBE Vector Filter - Trim","hd":false}],"ip":-1,"op":267,"st":-30,"ct":1,"bm":0},{"ddd":0,"ind":5,"ty":4,"nm":"Ebene 3 Konturen 3","sr":1,"ks":{"o":{"a":0,"k":100,"ix":11},"r":{"a":0,"k":0,"ix":10},"p":{"a":0,"k":[656.945,528.004,0],"ix":2,"l":2},"a":{"a":0,"k":[76.874,68.539,0],"ix":1,"l":2},"s":{"a":0,"k":[184,184,100],"ix":6,"l":2}},"ao":0,"shapes":[{"ty":"gr","it":[{"ind":0,"ty":"sh","ix":1,"ks":{"a":0,"k":{"i":[[16.294,-41.681],[15.094,0.957],[0.694,0.154],[1.124,2.646],[9.895,2.619],[4.866,-3.585],[-22.039,20.389],[-21.571,11.816],[0,0]],"o":[[-17.577,44.965],[-0.816,-0.052],[-3.421,-0.756],[-4.474,-10.54],[-8.038,-2.128],[0,0],[25.293,-23.398],[25.293,-13.854],[0,0]],"v":[[6.012,4.833],[-32.953,65.082],[-35.208,64.765],[-41.764,59.426],[-46.595,24.538],[-74.374,39.65],[-39.869,2.275],[24.736,-44.308],[74.374,-66.038]],"c":true},"ix":2},"nm":"Pfad 1","mn":"ADBE Vector Shape - Group","hd":false},{"ty":"st","c":{"a":0,"k":[0,0,0,1],"ix":3},"o":{"a":0,"k":100,"ix":4},"w":{"a":0,"k":1.08,"ix":5},"lc":2,"lj":1,"ml":10,"bm":0,"nm":"Kontur 1","mn":"ADBE Vector Graphic - Stroke","hd":false},{"ty":"fl","c":{"a":0,"k":[1,1,1,1],"ix":4},"o":{"a":0,"k":100,"ix":5},"r":1,"bm":0,"nm":"Fläche 1","mn":"ADBE Vector Graphic - Fill","hd":false},{"ty":"tr","p":{"a":0,"k":[76.874,68.539],"ix":2},"a":{"a":0,"k":[0,0],"ix":1},"s":{"a":0,"k":[100,100],"ix":3},"r":{"a":0,"k":0,"ix":6},"o":{"a":0,"k":100,"ix":7},"sk":{"a":0,"k":0,"ix":4},"sa":{"a":0,"k":0,"ix":5},"nm":"Transformieren"}],"nm":"Gruppe 1","np":3,"cix":2,"bm":0,"ix":1,"mn":"ADBE Vector Group","hd":false}],"ip":-1,"op":1744,"st":-1136,"ct":1,"bm":0},{"ddd":0,"ind":6,"ty":4,"nm":"Ebene 4 Konturen 3","sr":1,"ks":{"o":{"a":0,"k":100,"ix":11},"r":{"a":0,"k":0,"ix":10},"p":{"a":0,"k":[654.197,1435.991,0],"ix":2,"l":2},"a":{"a":0,"k":[76.739,68.71,0],"ix":1,"l":2},"s":{"a":0,"k":[184,184,100],"ix":6,"l":2}},"ao":0,"shapes":[{"ty":"gr","it":[{"ind":0,"ty":"sh","ix":1,"ks":{"a":0,"k":{"i":[[16.294,41.681],[15.094,-0.957],[0.694,-0.154],[1.124,-2.646],[9.895,-2.619],[4.866,3.585],[-22.039,-20.389],[-21.571,-11.816],[0,0]],"o":[[-17.577,-44.965],[-0.816,0.052],[-3.421,0.756],[-4.474,10.54],[-8.038,2.128],[0,0],[25.293,23.398],[25.293,13.854],[0,0]],"v":[[6.147,-5.005],[-32.818,-65.253],[-35.073,-64.937],[-41.629,-59.598],[-46.46,-24.709],[-74.239,-39.821],[-39.734,-2.447],[24.871,44.136],[74.239,66.21]],"c":true},"ix":2},"nm":"Pfad 1","mn":"ADBE Vector Shape - Group","hd":false},{"ty":"st","c":{"a":0,"k":[0,0,0,1],"ix":3},"o":{"a":0,"k":100,"ix":4},"w":{"a":0,"k":1.08,"ix":5},"lc":2,"lj":1,"ml":10,"bm":0,"nm":"Kontur 1","mn":"ADBE Vector Graphic - Stroke","hd":false},{"ty":"fl","c":{"a":0,"k":[1,1,1,1],"ix":4},"o":{"a":0,"k":100,"ix":5},"r":1,"bm":0,"nm":"Fläche 1","mn":"ADBE Vector Graphic - Fill","hd":false},{"ty":"tr","p":{"a":0,"k":[76.739,68.71],"ix":2},"a":{"a":0,"k":[0,0],"ix":1},"s":{"a":0,"k":[100,100],"ix":3},"r":{"a":0,"k":0,"ix":6},"o":{"a":0,"k":100,"ix":7},"sk":{"a":0,"k":0,"ix":4},"sa":{"a":0,"k":0,"ix":5},"nm":"Transformieren"}],"nm":"Gruppe 1","np":3,"cix":2,"bm":0,"ix":1,"mn":"ADBE Vector Group","hd":false}],"ip":-1,"op":1744,"st":-1136,"ct":1,"bm":0},{"ddd":0,"ind":7,"ty":4,"nm":".ciciliaryMuscleHighlight.highlighterIlluFill","cl":"ciciliaryMuscleHighlight highlighterIlluFill","sr":1,"ks":{"o":{"a":0,"k":100,"ix":11},"r":{"a":0,"k":0,"ix":10},"p":{"a":0,"k":[570.595,1280.046,0],"ix":2,"l":2},"a":{"a":0,"k":[20.976,29.013,0],"ix":1,"l":2},"s":{"a":0,"k":[184,184,100],"ix":6,"l":2}},"ao":0,"shapes":[{"ty":"gr","it":[{"ind":0,"ty":"sh","ix":1,"ks":{"a":0,"k":{"i":[[-4.159,0.492],[-1.424,10.315],[0,0],[10.435,-2.698],[0,0],[-4.871,-10.208],[-4.886,-5.694]],"o":[[-2.691,-4.813],[1.408,-10.191],[0,0],[-10.733,2.774],[0,0],[4.216,8.834],[1.123,-2.646]],"v":[[12.855,20.971],[8.415,-3.014],[18.476,-26.513],[2.046,-15.035],[-18.476,-21.23],[-9.777,5.406],[5.166,26.513]],"c":true},"ix":2},"nm":"Pfad 1","mn":"ADBE Vector Shape - Group","hd":false},{"ty":"st","c":{"a":0,"k":[0,0,0,1],"ix":3},"o":{"a":0,"k":100,"ix":4},"w":{"a":0,"k":1.08,"ix":5},"lc":2,"lj":1,"ml":10,"bm":0,"nm":"Kontur 1","mn":"ADBE Vector Graphic - Stroke","hd":false},{"ty":"fl","c":{"a":0,"k":[1,1,1,1],"ix":4},"o":{"a":0,"k":100,"ix":5},"r":1,"bm":0,"nm":"Fläche 1","mn":"ADBE Vector Graphic - Fill","hd":false},{"ty":"tr","p":{"a":0,"k":[20.976,29.013],"ix":2},"a":{"a":0,"k":[0,0],"ix":1},"s":{"a":0,"k":[100,100],"ix":3},"r":{"a":0,"k":0,"ix":6},"o":{"a":0,"k":100,"ix":7},"sk":{"a":0,"k":0,"ix":4},"sa":{"a":0,"k":0,"ix":5},"nm":"Transformieren"}],"nm":"Gruppe 1","np":3,"cix":2,"bm":0,"ix":1,"mn":"ADBE Vector Group","hd":false}],"ip":-1,"op":1744,"st":-1136,"ct":1,"bm":0},{"ddd":0,"ind":8,"ty":4,"nm":".ciciliaryMuscleHighlight.highlighterIlluFill","cl":"ciciliaryMuscleHighlight highlighterIlluFill","sr":1,"ks":{"o":{"a":0,"k":100,"ix":11},"r":{"a":0,"k":0,"ix":10},"p":{"a":0,"k":[570.595,672.949,0],"ix":2,"l":2},"a":{"a":0,"k":[20.976,29.671,0],"ix":1,"l":2},"s":{"a":0,"k":[184,184,100],"ix":6,"l":2}},"ao":0,"shapes":[{"ty":"gr","it":[{"ind":0,"ty":"sh","ix":1,"ks":{"a":0,"k":{"i":[[-4.159,-0.492],[-1.424,-10.315],[0,0],[10.435,2.698],[0,0],[-4.871,10.208],[-4.885,5.694]],"o":[[-2.691,4.813],[1.408,10.191],[0,0],[-10.733,-2.774],[0,0],[4.216,-8.834],[1.105,3.661]],"v":[[12.855,-20.313],[8.415,3.672],[18.476,27.171],[2.046,15.693],[-18.476,21.888],[-9.777,-4.748],[4.701,-27.171]],"c":true},"ix":2},"nm":"Pfad 1","mn":"ADBE Vector Shape - Group","hd":false},{"ty":"st","c":{"a":0,"k":[0,0,0,1],"ix":3},"o":{"a":0,"k":100,"ix":4},"w":{"a":0,"k":1.08,"ix":5},"lc":2,"lj":1,"ml":10,"bm":0,"nm":"Kontur 1","mn":"ADBE Vector Graphic - Stroke","hd":false},{"ty":"fl","c":{"a":0,"k":[1,1,1,1],"ix":4},"o":{"a":0,"k":100,"ix":5},"r":1,"bm":0,"nm":"Fläche 1","mn":"ADBE Vector Graphic - Fill","hd":false},{"ty":"tr","p":{"a":0,"k":[20.976,29.671],"ix":2},"a":{"a":0,"k":[0,0],"ix":1},"s":{"a":0,"k":[100,100],"ix":3},"r":{"a":0,"k":0,"ix":6},"o":{"a":0,"k":100,"ix":7},"sk":{"a":0,"k":0,"ix":4},"sa":{"a":0,"k":0,"ix":5},"nm":"Transformieren"}],"nm":"Gruppe 1","np":3,"cix":2,"bm":0,"ix":1,"mn":"ADBE Vector Group","hd":false}],"ip":-1,"op":1744,"st":-1136,"ct":1,"bm":0},{"ddd":0,"ind":9,"ty":4,"nm":".vitreousHumorousHighlight.highlighterIlluFill","cl":"vitreousHumorousHighlight highlighterIlluFill","sr":1,"ks":{"o":{"a":0,"k":100,"ix":11},"r":{"a":0,"k":0,"ix":10},"p":{"a":0,"k":[1030.606,980.262,0],"ix":2,"l":2},"a":{"a":0,"k":[276.201,322.687,0],"ix":1,"l":2},"s":{"a":0,"k":[184,184,100],"ix":6,"l":2}},"ao":0,"hasMask":true,"masksProperties":[{"inv":false,"mode":"s","pt":{"a":0,"k":{"i":[[-23.098,9.783],[0,0],[0,0],[31.112,19.26],[0,0],[3.261,57.609],[0,0]],"o":[[41.232,-17.463],[0,0],[0,0],[-99.865,-61.821],[0,0],[-3.261,-57.609],[0,0]],"v":[[148.155,4.61],[-102.389,67.11],[-226.302,645.371],[126.823,627.844],[19.35,445.371],[12.829,207.327],[94.078,48.903]],"c":true},"ix":1},"o":{"a":0,"k":100,"ix":3},"x":{"a":0,"k":0,"ix":4},"nm":"Maske 1"}],"shapes":[{"ty":"gr","it":[{"ind":0,"ty":"sh","ix":1,"ks":{"a":0,"k":{"i":[[4.162,20.806],[0,0],[0,0],[0.631,2.768],[0,0],[0,0],[1.312,4.692],[0,0],[0,0],[1.046,3.286],[0,0],[0,0],[138.878,0],[32.513,-17.847],[0,-127.1],[-94.891,-47.408],[-40.1,0],[0,176.834]],"o":[[0,0],[0,0],[-0.56,-2.795],[0,0],[0,0],[-1.105,-4.778],[0,0],[0,0],[-0.944,-3.332],[0,0],[0,0],[-41.248,-127.67],[-48.718,0],[-84.235,46.24],[0,135.896],[28.585,14.281],[173.219,0],[0,-22.061]],"v":[[266.836,-64.407],[266.837,-64.409],[266.826,-64.463],[265.035,-72.806],[264.943,-73.234],[264.773,-73.902],[261.154,-88.113],[261.098,-88.332],[260.862,-89.114],[257.868,-99.037],[257.472,-100.351],[257.448,-100.361],[-40.456,-320.187],[-168.807,-294.795],[-273.185,-3.385],[-151.264,301.665],[-40.456,320.187],[273.186,0]],"c":true},"ix":2},"nm":"Pfad 1","mn":"ADBE Vector Shape - Group","hd":false},{"ty":"st","c":{"a":0,"k":[0,0,0,1],"ix":3},"o":{"a":0,"k":100,"ix":4},"w":{"a":0,"k":1.08,"ix":5},"lc":2,"lj":1,"ml":10,"bm":0,"nm":"Kontur 1","mn":"ADBE Vector Graphic - Stroke","hd":false},{"ty":"fl","c":{"a":0,"k":[1,1,1,1],"ix":4},"o":{"a":0,"k":100,"ix":5},"r":1,"bm":0,"nm":"Fläche 1","mn":"ADBE Vector Graphic - Fill","hd":false},{"ty":"tr","p":{"a":0,"k":[275.685,322.687],"ix":2},"a":{"a":0,"k":[0,0],"ix":1},"s":{"a":0,"k":[100,100],"ix":3},"r":{"a":0,"k":0,"ix":6},"o":{"a":0,"k":100,"ix":7},"sk":{"a":0,"k":0,"ix":4},"sa":{"a":0,"k":0,"ix":5},"nm":"Transformieren"}],"nm":"Gruppe 1","np":3,"cix":2,"bm":0,"ix":1,"mn":"ADBE Vector Group","hd":false}],"ip":-1,"op":1744,"st":-1136,"ct":1,"bm":0},{"ddd":0,"ind":10,"ty":4,"nm":".foveaHighlight.highlighterIlluFill","cl":"foveaHighlight highlighterIlluFill","sr":1,"ks":{"o":{"a":0,"k":100,"ix":11},"r":{"a":0,"k":0,"ix":10},"p":{"a":0,"k":[1030.606,980.262,0],"ix":2,"l":2},"a":{"a":0,"k":[276.201,322.687,0],"ix":1,"l":2},"s":{"a":0,"k":[184,184,100],"ix":6,"l":2}},"ao":0,"shapes":[{"ty":"gr","it":[{"ind":0,"ty":"sh","ix":1,"ks":{"a":0,"k":{"i":[[4.801,-1.095],[1.834,8.038],[-4.8,1.095],[-1.834,-8.038]],"o":[[-4.801,1.095],[-1.834,-8.038],[4.801,-1.095],[1.835,8.038]],"v":[[3.32,14.553],[-8.692,1.984],[-3.321,-14.554],[8.691,-1.984]],"c":true},"ix":2},"nm":"Pfad 1","mn":"ADBE Vector Shape - Group","hd":false},{"ty":"st","c":{"a":0,"k":[0,0,0,1],"ix":3},"o":{"a":0,"k":100,"ix":4},"w":{"a":0,"k":1.08,"ix":5},"lc":2,"lj":1,"ml":10,"bm":0,"nm":"Kontur 1","mn":"ADBE Vector Graphic - Stroke","hd":false},{"ty":"fl","c":{"a":0,"k":[1,1,1,1],"ix":4},"o":{"a":0,"k":100,"ix":5},"r":1,"bm":0,"nm":"Fläche 1","mn":"ADBE Vector Graphic - Fill","hd":false},{"ty":"tr","p":{"a":0,"k":[539.375,240.186],"ix":2},"a":{"a":0,"k":[0,0],"ix":1},"s":{"a":0,"k":[100,100],"ix":3},"r":{"a":0,"k":0,"ix":6},"o":{"a":0,"k":100,"ix":7},"sk":{"a":0,"k":0,"ix":4},"sa":{"a":0,"k":0,"ix":5},"nm":"Transformieren"}],"nm":"Gruppe 2","np":3,"cix":2,"bm":0,"ix":1,"mn":"ADBE Vector Group","hd":false}],"ip":-2,"op":2876,"st":-4,"ct":1,"bm":0},{"ddd":0,"ind":11,"ty":4,"nm":".aqueousHumourHighlight.highlighterIlluFill","cl":"aqueousHumourHighlight highlighterIlluFill","sr":1,"ks":{"o":{"a":0,"k":100,"ix":11},"r":{"a":0,"k":0,"ix":10},"p":{"a":0,"k":[960,960,0],"ix":2,"l":2},"a":{"a":0,"k":[0,0,0],"ix":1,"l":2},"s":{"a":0,"k":[100,100,100],"ix":6,"l":2}},"ao":0,"shapes":[{"ty":"gr","it":[{"ind":0,"ty":"sh","ix":1,"ks":{"a":0,"k":{"i":[[0,0],[42.25,-61.25],[0,0],[0,0],[0,0],[-1.5,-5.25],[0,0],[0,0],[0,0],[0,0],[0,0],[0,0],[0,0]],"o":[[0,0],[-22.606,32.772],[0,0],[0,0],[0,0],[1.5,5.25],[0,0],[0,0],[0,0],[0,0],[0,0],[0,0],[0,0]],"v":[[-387.625,-397.25],[-466,-324.625],[-517,-222],[-537,-112],[-561,145],[-457.75,389.5],[-394,439.75],[-368.5,444],[-361,384],[-390,284],[-397,-175],[-386,-291],[-364.25,-338.375]],"c":true},"ix":2},"nm":"Pfad 1","mn":"ADBE Vector Shape - Group","hd":false},{"ty":"st","c":{"a":0,"k":[0,0,0,1],"ix":3},"o":{"a":0,"k":100,"ix":4},"w":{"a":0,"k":0,"ix":5},"lc":1,"lj":1,"ml":4,"bm":0,"nm":"Kontur 1","mn":"ADBE Vector Graphic - Stroke","hd":false},{"ty":"fl","c":{"a":0,"k":[1,1,1,1],"ix":4},"o":{"a":0,"k":100,"ix":5},"r":1,"bm":0,"nm":"Fläche 1","mn":"ADBE Vector Graphic - Fill","hd":false},{"ty":"tr","p":{"a":0,"k":[0,0],"ix":2},"a":{"a":0,"k":[0,0],"ix":1},"s":{"a":0,"k":[100,100],"ix":3},"r":{"a":0,"k":0,"ix":6},"o":{"a":0,"k":100,"ix":7},"sk":{"a":0,"k":0,"ix":4},"sa":{"a":0,"k":0,"ix":5},"nm":"Transformieren"}],"nm":"Form 1","np":3,"cix":2,"bm":0,"ix":1,"mn":"ADBE Vector Group","hd":false}],"ip":0,"op":228,"st":0,"ct":1,"bm":0},{"ddd":0,"ind":12,"ty":4,"nm":".foveaHighlight.highlighterIlluFill","cl":"foveaHighlight highlighterIlluFill","sr":1,"ks":{"o":{"a":0,"k":100,"ix":11},"r":{"a":0,"k":0,"ix":10},"p":{"a":0,"k":[970.431,953.414,0],"ix":2,"l":2},"a":{"a":0,"k":[0,0,0],"ix":1,"l":2},"s":{"a":0,"k":[100,100,100],"ix":6,"l":2}},"ao":0,"hasMask":true,"masksProperties":[{"inv":false,"mode":"a","pt":{"a":0,"k":{"i":[[11.598,0],[0,-16.051],[-11.598,0],[0,16.051]],"o":[[-11.598,0],[0,16.051],[11.598,0],[0,-16.051]],"v":[[534.944,-147.289],[513.944,-118.227],[534.944,-89.164],[555.944,-118.227]],"c":true},"ix":1},"o":{"a":0,"k":100,"ix":3},"x":{"a":0,"k":0,"ix":4},"nm":"Maske 1"}],"shapes":[{"ty":"gr","it":[{"d":1,"ty":"el","s":{"a":0,"k":[62,77],"ix":2},"p":{"a":0,"k":[0,0],"ix":3},"nm":"Elliptischer Pfad 1","mn":"ADBE Vector Shape - Ellipse","hd":false},{"ty":"st","c":{"a":0,"k":[0,0,0,1],"ix":3},"o":{"a":0,"k":100,"ix":4},"w":{"a":0,"k":0,"ix":5},"lc":1,"lj":1,"ml":4,"bm":0,"nm":"Kontur 1","mn":"ADBE Vector Graphic - Stroke","hd":false},{"ty":"fl","c":{"a":0,"k":[0.629529825846,0.377854650161,0.823529411765,1],"ix":4},"o":{"a":0,"k":100,"ix":5},"r":1,"bm":0,"nm":"Fläche 1","mn":"ADBE Vector Graphic - Fill","hd":false},{"ty":"tr","p":{"a":0,"k":[556.488,-127.191],"ix":2},"a":{"a":0,"k":[0,0],"ix":1},"s":{"a":0,"k":[100,100],"ix":3},"r":{"a":0,"k":0,"ix":6},"o":{"a":0,"k":100,"ix":7},"sk":{"a":0,"k":0,"ix":4},"sa":{"a":0,"k":0,"ix":5},"nm":"Transformieren"}],"nm":"Ellipse 1","np":3,"cix":2,"bm":0,"ix":1,"mn":"ADBE Vector Group","hd":false}],"ip":-36,"op":228,"st":-36,"ct":1,"bm":0},{"ddd":0,"ind":13,"ty":4,"nm":".retinaHighlight.highlighterIlluFill","cl":"retinaHighlight highlighterIlluFill","sr":1,"ks":{"o":{"a":1,"k":[{"i":{"x":[0.073],"y":[1]},"o":{"x":[0.73],"y":[0]},"t":-36,"s":[0]},{"t":-25,"s":[100]}],"ix":11},"r":{"a":0,"k":0,"ix":10},"p":{"a":0,"k":[976.212,981.612,0],"ix":2,"l":2},"a":{"a":0,"k":[596.583,601.738,0],"ix":1,"l":2},"s":{"a":0,"k":[100,100,100],"ix":6,"l":2}},"ao":0,"shapes":[{"ty":"gr","it":[{"ind":0,"ty":"sh","ix":1,"ks":{"a":1,"k":[{"i":{"x":0.667,"y":1},"o":{"x":0.333,"y":0},"t":-36,"s":[{"i":[[0,-361.746],[362.85,0],[120.487,146.648],[0,157.393],[-362.852,0]],"o":[[0,361.746],[-204.977,0],[-92.799,-112.949],[0,-361.746],[362.85,0]],"v":[[693.788,1.388],[36.789,656.388],[-471.728,416.157],[-620.212,1.388],[36.789,-653.612]],"c":true}]},{"i":{"x":0.833,"y":1},"o":{"x":0.333,"y":0},"t":-12,"s":[{"i":[[0,-329.569],[326.722,0],[108.49,133.603],[0,143.393],[-326.723,0]],"o":[[0,329.569],[-184.568,0],[-83.559,-102.902],[0,-329.569],[326.722,0]],"v":[[591.583,0],[0,596.738],[-457.884,377.876],[-591.583,0],[0,-596.738]],"c":true}]},{"t":118,"s":[{"i":[[0,-329.569],[326.722,0],[108.465,134.768],[0,142.453],[-326.723,0]],"o":[[0,329.569],[-185.501,0],[-82.575,-102.6],[0,-329.569],[326.722,0]],"v":[[591.583,0],[0,596.738],[-465.024,375.847],[-591.583,0],[0,-596.738]],"c":true}]}],"ix":2},"nm":"Pfad 1","mn":"ADBE Vector Shape - Group","hd":false},{"ty":"st","c":{"a":0,"k":[0,0,0,1],"ix":3},"o":{"a":0,"k":100,"ix":4},"w":{"a":0,"k":2,"ix":5},"lc":2,"lj":1,"ml":10,"bm":0,"nm":"Kontur 1","mn":"ADBE Vector Graphic - Stroke","hd":false},{"ty":"fl","c":{"a":0,"k":[1,1,1,1],"ix":4},"o":{"a":0,"k":100,"ix":5},"r":1,"bm":0,"nm":"Fläche 1","mn":"ADBE Vector Graphic - Fill","hd":false},{"ty":"tr","p":{"a":0,"k":[596.583,601.738],"ix":2},"a":{"a":0,"k":[0,0],"ix":1},"s":{"a":0,"k":[100,100],"ix":3},"r":{"a":0,"k":0,"ix":6},"o":{"a":0,"k":100,"ix":7},"sk":{"a":0,"k":0,"ix":4},"sa":{"a":0,"k":0,"ix":5},"nm":"Transformieren"}],"nm":"Gruppe 1","np":3,"cix":2,"bm":0,"ix":1,"mn":"ADBE Vector Group","hd":false}],"ip":-36,"op":228,"st":-36,"ct":1,"bm":0},{"ddd":0,"ind":14,"ty":4,"nm":".choroidHighlight.highlighterIlluFill","cl":"choroidHighlight highlighterIlluFill","sr":1,"ks":{"o":{"a":1,"k":[{"i":{"x":[0.073],"y":[1]},"o":{"x":[0.73],"y":[0]},"t":-36,"s":[0]},{"t":-25,"s":[100]}],"ix":11},"r":{"a":0,"k":0,"ix":10},"p":{"a":0,"k":[994.673,982.796,0],"ix":2,"l":2},"a":{"a":0,"k":[616.164,614.975,0],"ix":1,"l":2},"s":{"a":0,"k":[100,100,100],"ix":6,"l":2}},"ao":0,"shapes":[{"ty":"gr","it":[{"ind":0,"ty":"sh","ix":1,"ks":{"a":1,"k":[{"i":{"x":0.667,"y":1},"o":{"x":0.333,"y":0},"t":-36,"s":[{"i":[[0,-361.747],[362.85,0],[0,361.747],[-362.852,0]],"o":[[0,361.747],[-362.852,0],[0,-361.747],[362.85,0]],"v":[[673.328,0.204],[16.328,655.204],[-640.672,0.204],[16.328,-654.796]],"c":true}]},{"t":-12,"s":[{"i":[[0,-336.88],[337.536,0],[0,336.88],[-337.537,0]],"o":[[0,336.88],[-337.537,0],[0,-336.88],[337.536,0]],"v":[[611.164,0],[0.001,609.975],[-611.164,0],[0.001,-609.975]],"c":true}]}],"ix":2},"nm":"Pfad 1","mn":"ADBE Vector Shape - Group","hd":false},{"ty":"st","c":{"a":0,"k":[0,0,0,1],"ix":3},"o":{"a":0,"k":100,"ix":4},"w":{"a":0,"k":2,"ix":5},"lc":2,"lj":1,"ml":10,"bm":0,"nm":"Kontur 1","mn":"ADBE Vector Graphic - Stroke","hd":false},{"ty":"fl","c":{"a":0,"k":[1,1,1,1],"ix":4},"o":{"a":0,"k":100,"ix":5},"r":1,"bm":0,"nm":"Fläche 1","mn":"ADBE Vector Graphic - Fill","hd":false},{"ty":"tr","p":{"a":0,"k":[616.164,614.975],"ix":2},"a":{"a":0,"k":[0,0],"ix":1},"s":{"a":0,"k":[100,100],"ix":3},"r":{"a":0,"k":0,"ix":6},"o":{"a":0,"k":100,"ix":7},"sk":{"a":0,"k":0,"ix":4},"sa":{"a":0,"k":0,"ix":5},"nm":"Transformieren"}],"nm":"Gruppe 1","np":3,"cix":2,"bm":0,"ix":1,"mn":"ADBE Vector Group","hd":false}],"ip":-36,"op":228,"st":-36,"ct":1,"bm":0},{"ddd":0,"ind":15,"ty":4,"nm":"Ebene 11 Konturen 2","sr":1,"ks":{"o":{"a":0,"k":100,"ix":11},"r":{"a":0,"k":0,"ix":10},"p":{"s":true,"x":{"a":1,"k":[{"i":{"x":[0.709],"y":[1]},"o":{"x":[0.476],"y":[0]},"t":-108,"s":[1088.398]},{"i":{"x":[0.709],"y":[1]},"o":{"x":[0],"y":[0]},"t":-48,"s":[1011.773]},{"t":-36,"s":[1011.773]}],"ix":3},"y":{"a":1,"k":[{"i":{"x":[0.709],"y":[1]},"o":{"x":[0.476],"y":[0]},"t":-108,"s":[485.282]},{"i":{"x":[0.709],"y":[1]},"o":{"x":[0],"y":[0]},"t":-48,"s":[984.032]},{"t":-36,"s":[984.032]}],"ix":4}},"a":{"a":0,"k":[660.588,660.588,0],"ix":1,"l":2},"s":{"a":1,"k":[{"i":{"x":[0.511,0.511,0.667],"y":[1,1,1]},"o":{"x":[0.512,0.512,0.333],"y":[0,0,0]},"t":-108,"s":[11,11,100]},{"t":-36,"s":[100,100,100]}],"ix":6,"l":2}},"ao":0,"shapes":[{"ty":"gr","it":[{"ind":0,"ty":"sh","ix":1,"ks":{"a":1,"k":[{"i":{"x":0.667,"y":1},"o":{"x":0.333,"y":0},"t":-36,"s":[{"i":[[0,-362.071],[362.071,0],[0,362.071],[-362.071,0]],"o":[[0,362.071],[-362.071,0],[0,-362.071],[362.071,0]],"v":[[655.588,0],[0,655.588],[-655.588,0],[0,-655.588]],"c":true}]},{"t":-12,"s":[{"i":[[0,-352.375],[347.262,0],[0,352.375],[-347.262,0]],"o":[[0,352.375],[-347.262,0],[0,-352.375],[347.262,0]],"v":[[628.773,0],[0,638.032],[-628.773,0],[0,-638.032]],"c":true}]}],"ix":2},"nm":"Pfad 1","mn":"ADBE Vector Shape - Group","hd":false},{"ty":"st","c":{"a":0,"k":[0,0,0,1],"ix":3},"o":{"a":0,"k":100,"ix":4},"w":{"a":0,"k":2,"ix":5},"lc":2,"lj":1,"ml":10,"bm":0,"nm":"Kontur 1","mn":"ADBE Vector Graphic - Stroke","hd":false},{"ty":"tr","p":{"a":0,"k":[660.588,660.588],"ix":2},"a":{"a":0,"k":[0,0],"ix":1},"s":{"a":0,"k":[100,100],"ix":3},"r":{"a":0,"k":0,"ix":6},"o":{"a":0,"k":100,"ix":7},"sk":{"a":0,"k":0,"ix":4},"sa":{"a":0,"k":0,"ix":5},"nm":"Transformieren"}],"nm":"Gruppe 1","np":2,"cix":2,"bm":0,"ix":1,"mn":"ADBE Vector Group","hd":false}],"ip":-108,"op":228,"st":-36,"ct":1,"bm":0},{"ddd":0,"ind":16,"ty":4,"nm":".scleraHighlight.highlighterIlluFill","cl":"scleraHighlight highlighterIlluFill","sr":1,"ks":{"o":{"a":0,"k":100,"ix":11},"r":{"a":0,"k":0,"ix":10},"p":{"s":true,"x":{"a":1,"k":[{"i":{"x":[0.709],"y":[1]},"o":{"x":[0.476],"y":[0]},"t":-108,"s":[1088.398]},{"i":{"x":[0.709],"y":[1]},"o":{"x":[0],"y":[0]},"t":-48,"s":[1009.523]},{"t":-36,"s":[1009.523]}],"ix":3},"y":{"a":1,"k":[{"i":{"x":[0.709],"y":[1]},"o":{"x":[0.476],"y":[0]},"t":-108,"s":[485.282]},{"i":{"x":[0.709],"y":[1]},"o":{"x":[0],"y":[0]},"t":-48,"s":[984.032]},{"t":-36,"s":[984.032]}],"ix":4}},"a":{"a":0,"k":[660.588,660.588,0],"ix":1,"l":2},"s":{"a":1,"k":[{"i":{"x":[0.511,0.511,0.667],"y":[1,1,1]},"o":{"x":[0.512,0.512,0.333],"y":[0,0,0]},"t":-108,"s":[11,11,100]},{"t":-36,"s":[100,100,100]}],"ix":6,"l":2}},"ao":0,"shapes":[{"ty":"gr","it":[{"ind":0,"ty":"sh","ix":1,"ks":{"a":1,"k":[{"i":{"x":0.667,"y":1},"o":{"x":0.333,"y":0},"t":-36,"s":[{"i":[[0,-362.071],[362.071,0],[0,362.071],[-362.071,0]],"o":[[0,362.071],[-362.071,0],[0,-362.071],[362.071,0]],"v":[[655.588,0],[0,655.588],[-655.588,0],[0,-655.588]],"c":true}]},{"t":-12,"s":[{"i":[[0,-352.375],[347.18,0],[0,352.375],[-347.18,0]],"o":[[0,352.375],[-347.18,0],[0,-352.375],[347.18,0]],"v":[[630.477,0],[1.851,638.032],[-626.773,0],[1.851,-638.032]],"c":true}]}],"ix":2},"nm":"Pfad 1","mn":"ADBE Vector Shape - Group","hd":false},{"ty":"fl","c":{"a":0,"k":[1,1,1,1],"ix":4},"o":{"a":0,"k":100,"ix":5},"r":1,"bm":0,"nm":"Fläche 1","mn":"ADBE Vector Graphic - Fill","hd":false},{"ty":"tr","p":{"a":0,"k":[660.588,660.588],"ix":2},"a":{"a":0,"k":[0,0],"ix":1},"s":{"a":0,"k":[100,100],"ix":3},"r":{"a":0,"k":0,"ix":6},"o":{"a":0,"k":100,"ix":7},"sk":{"a":0,"k":0,"ix":4},"sa":{"a":0,"k":0,"ix":5},"nm":"Transformieren"}],"nm":"Gruppe 1","np":2,"cix":2,"bm":0,"ix":1,"mn":"ADBE Vector Group","hd":false}],"ip":-108,"op":228,"st":-36,"ct":1,"bm":0},{"ddd":0,"ind":17,"ty":4,"nm":".aqueuousHumourHighlight.highlighterIlluFill","cl":"aqueuousHumourHighlight highlighterIlluFill","sr":1,"ks":{"o":{"a":0,"k":100,"ix":11},"r":{"a":0,"k":0,"ix":10},"p":{"s":true,"x":{"a":1,"k":[{"i":{"x":[0.123],"y":[1]},"o":{"x":[0.697],"y":[0]},"t":-24,"s":[758.718]},{"t":-12,"s":[658.718]}],"ix":3},"y":{"a":0,"k":981.282,"ix":4}},"a":{"a":0,"k":[339.97,433.678,0],"ix":1,"l":2},"s":{"a":0,"k":[100,100,100],"ix":6,"l":2}},"ao":0,"shapes":[{"ty":"gr","it":[{"ind":0,"ty":"sh","ix":1,"ks":{"a":0,"k":{"i":[[0,-236.752],[184.999,0],[0,236.752],[-184.998,0]],"o":[[0,236.752],[-184.998,0],[0,-236.752],[184.999,0]],"v":[[334.969,0],[-0.001,428.678],[-334.97,0],[-0.001,-428.678]],"c":true},"ix":2},"nm":"Pfad 1","mn":"ADBE Vector Shape - Group","hd":false},{"ty":"st","c":{"a":0,"k":[0,0,0,1],"ix":3},"o":{"a":0,"k":100,"ix":4},"w":{"a":0,"k":2,"ix":5},"lc":2,"lj":1,"ml":10,"bm":0,"nm":"Kontur 1","mn":"ADBE Vector Graphic - Stroke","hd":false},{"ty":"tr","p":{"a":0,"k":[339.969,433.678],"ix":2},"a":{"a":0,"k":[0,0],"ix":1},"s":{"a":0,"k":[100,100],"ix":3},"r":{"a":0,"k":0,"ix":6},"o":{"a":0,"k":100,"ix":7},"sk":{"a":0,"k":0,"ix":4},"sa":{"a":0,"k":0,"ix":5},"nm":"Transformieren"}],"nm":"Gruppe 1","np":2,"cix":2,"bm":0,"ix":1,"mn":"ADBE Vector Group","hd":false},{"ty":"fl","c":{"a":0,"k":[1,1,1,1],"ix":4},"o":{"a":0,"k":100,"ix":5},"r":1,"bm":0,"nm":"Fläche 1","mn":"ADBE Vector Graphic - Fill","hd":false}],"ip":-36,"op":228,"st":-36,"ct":1,"bm":0},{"ddd":0,"ind":18,"ty":4,"nm":".corneaHighlight.highlighterIlluFill","cl":"corneaHighlight highlighterIlluFill","sr":1,"ks":{"o":{"a":0,"k":100,"ix":11},"r":{"a":0,"k":0,"ix":10},"p":{"s":true,"x":{"a":1,"k":[{"i":{"x":[0.123],"y":[1]},"o":{"x":[0.697],"y":[0]},"t":-24,"s":[750.414]},{"t":-12,"s":[670.414]}],"ix":3},"y":{"a":0,"k":981.282,"ix":4}},"a":{"a":0,"k":[372.439,433.678,0],"ix":1,"l":2},"s":{"a":0,"k":[100,100,100],"ix":6,"l":2}},"ao":0,"shapes":[{"ty":"gr","it":[{"ind":0,"ty":"sh","ix":1,"ks":{"a":0,"k":{"i":[[0,-236.752],[202.93,0],[0,236.752],[-202.931,0]],"o":[[0,236.752],[-202.931,0],[0,-236.752],[202.93,0]],"v":[[367.439,0],[0.001,428.678],[-367.439,0],[0.001,-428.678]],"c":true},"ix":2},"nm":"Pfad 1","mn":"ADBE Vector Shape - Group","hd":false},{"ty":"st","c":{"a":0,"k":[0,0,0,1],"ix":3},"o":{"a":0,"k":100,"ix":4},"w":{"a":0,"k":2,"ix":5},"lc":2,"lj":1,"ml":10,"bm":0,"nm":"Kontur 1","mn":"ADBE Vector Graphic - Stroke","hd":false},{"ty":"tr","p":{"a":0,"k":[372.439,433.678],"ix":2},"a":{"a":0,"k":[0,0],"ix":1},"s":{"a":0,"k":[100,100],"ix":3},"r":{"a":0,"k":0,"ix":6},"o":{"a":0,"k":100,"ix":7},"sk":{"a":0,"k":0,"ix":4},"sa":{"a":0,"k":0,"ix":5},"nm":"Transformieren"}],"nm":"Gruppe 1","np":2,"cix":2,"bm":0,"ix":1,"mn":"ADBE Vector Group","hd":false},{"ty":"fl","c":{"a":0,"k":[1,1,1,1],"ix":4},"o":{"a":0,"k":100,"ix":5},"r":1,"bm":0,"nm":"Fläche 1","mn":"ADBE Vector Graphic - Fill","hd":false}],"ip":-36,"op":228,"st":-36,"ct":1,"bm":0},{"ddd":0,"ind":19,"ty":4,"nm":".opticNerveHighlight.highlighterIlluFill","cl":"opticNerveHighlight highlighterIlluFill","sr":1,"ks":{"o":{"a":0,"k":100,"ix":11},"r":{"a":0,"k":0,"ix":10},"p":{"s":true,"x":{"a":1,"k":[{"i":{"x":[0.123],"y":[1]},"o":{"x":[0.697],"y":[0]},"t":-24,"s":[1486.297]},{"t":-12,"s":[1622.297]}],"ix":3},"y":{"a":0,"k":1061.205,"ix":4}},"a":{"a":0,"k":[107.19,54.302,0],"ix":1,"l":2},"s":{"a":0,"k":[100,100,100],"ix":6,"l":2}},"ao":0,"shapes":[{"ty":"gr","it":[{"ind":0,"ty":"sh","ix":1,"ks":{"a":0,"k":{"i":[[0,0],[0,0],[0,0],[0,0]],"o":[[0,0],[0,0],[0,0],[0,0]],"v":[[105.776,52.888],[-105.776,52.888],[-105.776,-52.888],[105.776,-52.888]],"c":true},"ix":2},"nm":"Pfad 1","mn":"ADBE Vector Shape - Group","hd":false},{"ty":"st","c":{"a":0,"k":[0,0,0,1],"ix":3},"o":{"a":0,"k":100,"ix":4},"w":{"a":0,"k":2,"ix":5},"lc":2,"lj":1,"ml":10,"bm":0,"nm":"Kontur 1","mn":"ADBE Vector Graphic - Stroke","hd":false},{"ty":"fl","c":{"a":0,"k":[1,1,1,1],"ix":4},"o":{"a":0,"k":100,"ix":5},"r":1,"bm":0,"nm":"Fläche 1","mn":"ADBE Vector Graphic - Fill","hd":false},{"ty":"tr","p":{"a":0,"k":[107.19,54.302],"ix":2},"a":{"a":0,"k":[0,0],"ix":1},"s":{"a":0,"k":[100,100],"ix":3},"r":{"a":0,"k":0,"ix":6},"o":{"a":0,"k":100,"ix":7},"sk":{"a":0,"k":0,"ix":4},"sa":{"a":0,"k":0,"ix":5},"nm":"Transformieren"}],"nm":"Gruppe 1","np":3,"cix":2,"bm":0,"ix":1,"mn":"ADBE Vector Group","hd":false}],"ip":-36,"op":228,"st":-36,"ct":1,"bm":0}],"markers":[]}